arcade_cli/__init__.py
arcade_cli/authn.py
arcade_cli/config.py
arcade_cli/configure.py
arcade_cli/constants.py
arcade_cli/deploy.py
arcade_cli/display.py
arcade_cli/evals_runner.py
arcade_cli/main.py
arcade_cli/new.py
arcade_cli/org.py
arcade_cli/project.py
arcade_cli/secret.py
arcade_cli/server.py
arcade_cli/show.py
arcade_cli/utils.py
arcade_cli/formatters/__init__.py
arcade_cli/formatters/base.py
arcade_cli/formatters/html.py
arcade_cli/formatters/json.py
arcade_cli/formatters/markdown.py
arcade_cli/formatters/text.py
arcade_cli/templates/__init__.py
arcade_cli/templates/base.jinja
arcade_cli/templates/cli_login_failed.jinja
arcade_cli/templates/cli_login_success.jinja
arcade_cli/templates/full/{{ toolkit_name }}/.pre-commit-config.yaml
arcade_cli/templates/full/{{ toolkit_name }}/.ruff.toml
arcade_cli/templates/full/{{ toolkit_name }}/LICENSE
arcade_cli/templates/full/{{ toolkit_name }}/Makefile
arcade_cli/templates/full/{{ toolkit_name }}/README.md
arcade_cli/templates/full/{{ toolkit_name }}/pyproject.toml
arcade_cli/templates/full/{{ toolkit_name }}/evals/eval_{{ toolkit_name }}.py
arcade_cli/templates/full/{{ toolkit_name }}/tests/__init__.py
arcade_cli/templates/full/{{ toolkit_name }}/tests/test_{{ toolkit_name }}.py
arcade_cli/templates/full/{{ toolkit_name }}/{{ package_name }}/__init__.py
arcade_cli/templates/full/{{ toolkit_name }}/{{ package_name }}/tools/__init__.py
arcade_cli/templates/full/{{ toolkit_name }}/{{ package_name }}/tools/hello.py
arcade_cli/templates/minimal/{{ toolkit_name }}/pyproject.toml
arcade_cli/templates/minimal/{{ toolkit_name }}/src/{{ toolkit_name }}/.env.example
arcade_cli/templates/minimal/{{ toolkit_name }}/src/{{ toolkit_name }}/__init__.py
arcade_cli/templates/minimal/{{ toolkit_name }}/src/{{ toolkit_name }}/server.py
arcade_cli/usage/command_tracker.py
arcade_cli/usage/constants.py
arcade_evals/__init__.py
arcade_evals/capture.py
arcade_evals/critic.py
arcade_evals/errors.py
arcade_evals/eval.py
arcade_mcp-1.8.3.dist-info/METADATA
arcade_mcp-1.8.3.dist-info/WHEEL
arcade_mcp-1.8.3.dist-info/entry_points.txt
arcade_mcp-1.8.3.dist-info/licenses/LICENSE
arcade_mcp-1.8.3.dist-info/RECORD
