Metadata-Version: 2.4
Name: arcade-mcp
Version: 1.8.3
Summary: Arcade.dev - Tool Calling platform for Agents
Author-email: Arcade <dev@arcade.dev>
License: MIT License
License-File: LICENSE
Classifier: Development Status :: 5 - Production/Stable
Classifier: Intended Audience :: Developers
Classifier: License :: OSI Approved :: MIT License
Classifier: Programming Language :: Python :: 3
Classifier: Programming Language :: Python :: 3.10
Classifier: Programming Language :: Python :: 3.11
Classifier: Programming Language :: Python :: 3.12
Classifier: Programming Language :: Python :: 3.13
Requires-Python: >=3.10
Requires-Dist: arcade-core<5.0.0,>=4.2.2
Requires-Dist: arcade-mcp-server<2.0.0,>=1.15.1
Requires-Dist: arcadepy==1.8.0
Requires-Dist: authlib==1.6.6
Requires-Dist: click==8.1.8
Requires-Dist: jinja2==3.1.6
Requires-Dist: python-dateutil>=2.8.2
Requires-Dist: rich<15.0.0,>=14.0.0
Requires-Dist: tqdm==4.67.1
Requires-Dist: typer==0.10.0
Provides-Extra: all
Requires-Dist: anthropic>=0.40.0; extra == 'all'
Requires-Dist: arcade-mcp-server<2.0.0,>=1.14.0; extra == 'all'
Requires-Dist: arcade-serve<4.0.0,>=3.2.0; extra == 'all'
Requires-Dist: arcade-tdk<4.0.0,>=3.4.0; extra == 'all'
Requires-Dist: mcp>=1.9.0; extra == 'all'
Requires-Dist: numpy>=2.0.0; extra == 'all'
Requires-Dist: openai==1.82.1; extra == 'all'
Requires-Dist: pytz>=2024.1; extra == 'all'
Requires-Dist: scikit-learn>=1.5.0; extra == 'all'
Requires-Dist: scipy>=1.14.0; extra == 'all'
Provides-Extra: evals
Requires-Dist: anthropic>=0.40.0; extra == 'evals'
Requires-Dist: mcp>=1.9.0; extra == 'evals'
Requires-Dist: numpy>=2.0.0; extra == 'evals'
Requires-Dist: openai==1.82.1; extra == 'evals'
Requires-Dist: pytz>=2024.1; extra == 'evals'
Requires-Dist: scikit-learn>=1.5.0; extra == 'evals'
Requires-Dist: scipy>=1.14.0; extra == 'evals'
